biokeen/__init__.py
biokeen/__main__.py
biokeen/constants.py
biokeen/content.py
biokeen/convert.py
biokeen/cli/__init__.py
biokeen/cli/__main__.py
biokeen/cli/cli.py
biokeen/cli/messages.py
biokeen/cli/prompts.py
biokeen/convert/__init__.py
biokeen/convert/converters.py
biokeen/convert/io.py
biokeen-0.0.14.dist-info/LICENSE
biokeen-0.0.14.dist-info/METADATA
biokeen-0.0.14.dist-info/WHEEL
biokeen-0.0.14.dist-info/entry_points.txt
biokeen-0.0.14.dist-info/top_level.txt
biokeen-0.0.14.dist-info/RECORD
