Metadata-Version: 2.1
Name: biokeen
Version: 0.0.14
Summary: A package for training and evaluating biological knowledge graph embeddings
Home-page: https://github.com/SmartDataAnalytics/BioKEEN
Author: Mehdi Ali
Author-email: mehdi.ali@cs.uni-bonn.de
Maintainer: Mehdi Ali
Maintainer-email: mehdi.ali@cs.uni-bonn.de
License: MIT
Download-URL: https://github.com/SmartDataAnalytics/BioKEEN/releases
Project-URL: Bug Tracker, https://github.com/SmartDataAnalytics/BioKEEN/issues
Project-URL: Documentation, https://biokeen.readthedocs.io
Keywords: KEEN,knowledge embedding
Platform: UNKNOWN
Classifier: Development Status :: 1 - Planning
Classifier: Intended Audience :: Developers
Classifier: License :: OSI Approved :: MIT License
Classifier: Programming Language :: Python
Classifier: Programming Language :: Python :: 3.7
Classifier: Programming Language :: Python :: 3.6
Classifier: Programming Language :: Python :: 3 :: Only
Requires-Python: >=3.6
Requires-Dist: mock
Requires-Dist: pybel (<0.14.0)
Requires-Dist: bio2bel (<0.3.0)
Requires-Dist: tqdm
Requires-Dist: pandas
Requires-Dist: pykeen
Requires-Dist: click-default-group
Requires-Dist: click
Provides-Extra: docs
Requires-Dist: sphinx ; extra == 'docs'
Requires-Dist: sphinx-rtd-theme ; extra == 'docs'
Requires-Dist: sphinx-click ; extra == 'docs'
Requires-Dist: sphinx-autodoc-typehints ; extra == 'docs'
